{
  "SamplesAnalysisID": "opendes:work-product-component--SamplesAnalysis:IsotopeAnalysis_WPC:",
  "SampleID": "opendes:master-data--Sample:IsotopeAnalysis_Sample:",
  "Method": "opendes:reference-data--BulkPyrolysisMethod:HAWK:",
  "IsotopeAnalysisData": [
    {
      "Component": "opendes:reference-data--NonGasIsotopeComponents:Carbonate:",
      "IsotopeRatio": [
        {
          "Element": "opendes:reference-data--IsotopeRatioElements:C12:",
          "AtomicNumber": 6,
          "Value": 12,
          "UnitOfMeasure": "opendes:reference-data--UnitOfMeasure:%25:"
        }
      ]
    },
    {
      "Component": "opendes:reference-data--GasIsotopeComponents:GasIsotopeComponent:CH4:",
      "IsotopeRatio": [
        {
          "Element": "opendes:reference-data--IsotopeRatioElements:C14:",
          "AtomicNumber": 6,
          "Value": 14.0,
          "UnitOfMeasure": "opendes:reference-data--UnitOfMeasure:%25:"
        }
      ]
    },
    {
      "Component": "opendes:reference-data--CompoundSpecificIsotopeComponents:nc2:",
      "IsotopeRatio": [
        {
          "Element": "opendes:reference-data--IsotopeRatioElements:C13:",
          "AtomicNumber": 6,
          "Value": 13.0,
          "UnitOfMeasure": "opendes:reference-data--UnitOfMeasure:%25:"
        }
      ]
    }
  ],
  "$id": "isotope_analysis_example.1.0.0.json"
}
